{"id":1508129753035,"drawData":[{"flickr":{"id":"14381563712","owner":"29295370@N07","secret":"11480af02b","server":"2928","farm":3,"title":"'Nordic Chieftain' sliding down the ways","thumb":"https:\/\/farm3.staticflickr.com\/2928\/14381563712_11480af02b_n.jpg"},"draw":[{"src":"http:\/\/mtchl.net\/succession\/proxy.php?url=https:\/\/farm3.staticflickr.com\/2928\/14381563712_11480af02b_b.jpg","xp":0,"yp":-292,"w":1000,"h":1282,"comp":"source-over","alpha":1}]},{"flickr":{"id":"14753735836","owner":"126377022@N07","secret":"71a235d6c9","server":"3860","farm":4,"title":"Image from page 496 of \"A treatise on wood engravings : historical and practical\" (1881)","thumb":"https:\/\/farm4.staticflickr.com\/3860\/14753735836_71a235d6c9_n.jpg"},"draw":[{"src":"http:\/\/mtchl.net\/succession\/proxy.php?url=https:\/\/farm4.staticflickr.com\/3860\/14753735836_71a235d6c9_b.jpg","xp":195,"yp":188,"w":146,"h":143,"comp":"multiply","alpha":0.6},{"src":"http:\/\/mtchl.net\/succession\/proxy.php?url=https:\/\/farm4.staticflickr.com\/3860\/14753735836_71a235d6c9_b.jpg","xp":195,"yp":376,"w":146,"h":143,"comp":"multiply","alpha":0.6},{"src":"http:\/\/mtchl.net\/succession\/proxy.php?url=https:\/\/farm4.staticflickr.com\/3860\/14753735836_71a235d6c9_b.jpg","xp":195,"yp":564,"w":146,"h":143,"comp":"multiply","alpha":0.6},{"src":"http:\/\/mtchl.net\/succession\/proxy.php?url=https:\/\/farm4.staticflickr.com\/3860\/14753735836_71a235d6c9_b.jpg","xp":195,"yp":752,"w":146,"h":143,"comp":"multiply","alpha":0.6},{"src":"http:\/\/mtchl.net\/succession\/proxy.php?url=https:\/\/farm4.staticflickr.com\/3860\/14753735836_71a235d6c9_b.jpg","xp":195,"yp":940,"w":146,"h":143,"comp":"multiply","alpha":0.6},{"src":"http:\/\/mtchl.net\/succession\/proxy.php?url=https:\/\/farm4.staticflickr.com\/3860\/14753735836_71a235d6c9_b.jpg","xp":195,"yp":1128,"w":146,"h":143,"comp":"multiply","alpha":0.6}]},{"flickr":{"id":"14777718014","owner":"126377022@N07","secret":"347b9ca821","server":"2919","farm":3,"title":"Image from page 139 of \"The great war in England in 1897\" (1895)","thumb":"https:\/\/farm3.staticflickr.com\/2919\/14777718014_347b9ca821_n.jpg"},"draw":[{"src":"http:\/\/mtchl.net\/succession\/proxy.php?url=https:\/\/farm3.staticflickr.com\/2919\/14777718014_347b9ca821_b.jpg","xp":0,"yp":-452,"w":1000,"h":1602,"comp":"multiply","alpha":0.6}]},{"flickr":{"id":"15176273591","owner":"29295370@N07","secret":"a207041d85","server":"3890","farm":4,"title":"Mouth of the River Tyne, 1949","thumb":"https:\/\/farm4.staticflickr.com\/3890\/15176273591_a207041d85_n.jpg"},"draw":[{"src":"http:\/\/mtchl.net\/succession\/proxy.php?url=https:\/\/farm4.staticflickr.com\/3890\/15176273591_a207041d85_b.jpg","xp":40,"yp":0,"w":919,"h":700,"comp":"darken","alpha":0.6}]},{"flickr":{"id":"14591827960","owner":"126377022@N07","secret":"12cf725319","server":"5581","farm":6,"title":"Image from page 467 of \"Photographic pedigree of the descendants of Isaac and Rachel Wilson\" (1912)","thumb":"https:\/\/farm6.staticflickr.com\/5581\/14591827960_12cf725319_n.jpg"},"draw":[{"src":"http:\/\/mtchl.net\/succession\/proxy.php?url=https:\/\/farm6.staticflickr.com\/5581\/14591827960_12cf725319_b.jpg","xp":132,"yp":587,"w":106,"h":106,"comp":"multiply","alpha":0.6},{"src":"http:\/\/mtchl.net\/succession\/proxy.php?url=https:\/\/farm6.staticflickr.com\/5581\/14591827960_12cf725319_b.jpg","xp":264,"yp":587,"w":106,"h":106,"comp":"multiply","alpha":0.6},{"src":"http:\/\/mtchl.net\/succession\/proxy.php?url=https:\/\/farm6.staticflickr.com\/5581\/14591827960_12cf725319_b.jpg","xp":396,"yp":587,"w":106,"h":106,"comp":"multiply","alpha":0.6},{"src":"http:\/\/mtchl.net\/succession\/proxy.php?url=https:\/\/farm6.staticflickr.com\/5581\/14591827960_12cf725319_b.jpg","xp":528,"yp":587,"w":106,"h":106,"comp":"multiply","alpha":0.6},{"src":"http:\/\/mtchl.net\/succession\/proxy.php?url=https:\/\/farm6.staticflickr.com\/5581\/14591827960_12cf725319_b.jpg","xp":660,"yp":587,"w":106,"h":106,"comp":"multiply","alpha":0.6},{"src":"http:\/\/mtchl.net\/succession\/proxy.php?url=https:\/\/farm6.staticflickr.com\/5581\/14591827960_12cf725319_b.jpg","xp":792,"yp":587,"w":106,"h":106,"comp":"multiply","alpha":0.6},{"src":"http:\/\/mtchl.net\/succession\/proxy.php?url=https:\/\/farm6.staticflickr.com\/5581\/14591827960_12cf725319_b.jpg","xp":924,"yp":587,"w":106,"h":106,"comp":"multiply","alpha":0.6}]}]}